bitbucket_code_insight_reporter/__init__.py
bitbucket_code_insight_reporter/bitbucket.py
bitbucket_code_insight_reporter/generate.py
bitbucket_code_insight_reporter/report.py
bitbucket_code_insight_reporter-0.2.0.dist-info/METADATA
bitbucket_code_insight_reporter-0.2.0.dist-info/WHEEL
bitbucket_code_insight_reporter-0.2.0.dist-info/entry_points.txt
bitbucket_code_insight_reporter-0.2.0.dist-info/top_level.txt
bitbucket_code_insight_reporter-0.2.0.dist-info/zip-safe
bitbucket_code_insight_reporter-0.2.0.dist-info/RECORD
