Metadata-Version: 2.1
Name: bitbucket-code-insight-reporter
Version: 0.2.0
Summary: Allows for parsing LLVM Diagnostics output and create BB code insights accordingly
Home-page: https://github.com/KevinDeJong-TomTom/bitbucket-code-insight-reporter
Author: Kevin de Jong
Author-email: KevinDeJong@tomtom.com
License: Apache License 2.0
Download-URL: https://github.com/KevinDeJong-TomTom/bitbucket-code-insight-reporter
Keywords: diagnostics codeinsights insights bitbucket llvm
Platform: UNKNOWN
Requires-Python: >=3.5
Requires-Dist: Click (<8,>=7)
Requires-Dist: llvm-diagnostics (<1,>=0)
Requires-Dist: requests (<3,>=2.25.1)
